Metadata-Version: 2.1
Name: vpp-papi.stable
Version: 20.9.1
Summary: VPP Python binding
Home-page: https://wiki.fd.io/view/VPP/Python_API
Author: Ole Troan
Author-email: ot@cisco.com
License: Apache-2.0
Platform: UNKNOWN
Requires-Dist: cffi (>=1.6)
